maquina_fluxo/__init__.py
maquina_fluxo/fluxo.py
maquina_fluxo-0.0.1.dist-info/METADATA
maquina_fluxo-0.0.1.dist-info/WHEEL
maquina_fluxo-0.0.1.dist-info/top_level.txt
maquina_fluxo-0.0.1.dist-info/RECORD
