Metadata-Version: 2.1
Name: maquina-fluxo
Version: 0.0.1
Summary: Calculo perda de carga
Home-page: https://github.com/erickhiroyuki/Projeto-3-CD
Author: Erick
Author-email: erickhiroyuki@alunos.utfpr.edu.br
Requires-Python: >=3.10.8
Requires-Dist: colebrook (==0.0.5)
Requires-Dist: matplotlib (==3.6.1)
Requires-Dist: numpy (==1.23.4)
